restrun/__init__.py
restrun/__main__.py
restrun/cli/__init__.py
restrun/cli/app.py
restrun/cli/commands/__init__.py
restrun/cli/commands/create/__init__.py
restrun/cli/commands/create/config.py
restrun/cli/commands/create/operation.py
restrun/cli/commands/generate.py
restrun/cli/commands/get/__init__.py
restrun/cli/commands/get/config.py
restrun/cli/commands/new.py
restrun/cli/prompt/__init__.py
restrun/cli/prompt/config.py
restrun/cli/prompt/operation_method.py
restrun/cli/prompt/project_name.py
restrun/cli/prompt/resource_path.py
restrun/cli/prompt/select.py
restrun/cli/prompt/source.py
restrun/config/__init__.py
restrun/config/v1/__init__.py
restrun/config/v1/format/__init__.py
restrun/config/v1/format/black_config.py
restrun/config/v1/format/isort_config.py
restrun/config/v1/lint/__init__.py
restrun/config/v1/lint/ruff_config.py
restrun/config/v1/source/__init__.py
restrun/config/v1/source/openapi_source.py
restrun/core/__init__.py
restrun/core/client.py
restrun/core/http.py
restrun/core/httpx.py
restrun/core/model.py
restrun/core/operation.py
restrun/core/resource.py
restrun/exceptions.py
restrun/formatter/__init__.py
restrun/formatter/black.py
restrun/formatter/formatter.py
restrun/formatter/isort.py
restrun/generator/__init__.py
restrun/generator/client.py
restrun/generator/client.py.jinja
restrun/generator/client_mixins_module.py
restrun/generator/client_mixins_module.py.jinja
restrun/generator/client_module.py
restrun/generator/client_module.py.jinja
restrun/generator/context/__init__.py
restrun/generator/context/operation_context.py
restrun/generator/context/resource_context.py
restrun/generator/context/resources_context.py
restrun/generator/context/restrun_context.py
restrun/generator/context/schema_context.py
restrun/generator/login/__init__.py
restrun/generator/login/bearer_token.py
restrun/generator/mock_client.py
restrun/generator/mock_client.py.jinja
restrun/generator/operation.py
restrun/generator/operation.py.jinja
restrun/generator/real_client.py
restrun-0.1.0.dist-info/METADATA
restrun-0.1.0.dist-info/WHEEL
restrun-0.1.0.dist-info/entry_points.txt
restrun-0.1.0.dist-info/RECORD
